odoo10_addon_auth_signup_verify_email-10.0.2.0.0-py2.7-nspkg.pth
odoo/addons/auth_signup_verify_email/README.rst
odoo/addons/auth_signup_verify_email/__init__.py
odoo/addons/auth_signup_verify_email/__manifest__.py
odoo/addons/auth_signup_verify_email/controllers/__init__.py
odoo/addons/auth_signup_verify_email/controllers/main.py
odoo/addons/auth_signup_verify_email/i18n/de.po
odoo/addons/auth_signup_verify_email/i18n/es.po
odoo/addons/auth_signup_verify_email/i18n/fr.po
odoo/addons/auth_signup_verify_email/i18n/hr.po
odoo/addons/auth_signup_verify_email/i18n/hr_HR.po
odoo/addons/auth_signup_verify_email/i18n/it.po
odoo/addons/auth_signup_verify_email/i18n/pt_BR.po
odoo/addons/auth_signup_verify_email/i18n/ro.po
odoo/addons/auth_signup_verify_email/i18n/sl.po
odoo/addons/auth_signup_verify_email/i18n/tr.po
odoo/addons/auth_signup_verify_email/static/description/icon.png
odoo/addons/auth_signup_verify_email/static/description/icon.svg
odoo/addons/auth_signup_verify_email/tests/__init__.py
odoo/addons/auth_signup_verify_email/tests/test_verify_email.py
odoo/addons/auth_signup_verify_email/views/signup.xml
odoo10_addon_auth_signup_verify_email-10.0.2.0.0.dist-info/DESCRIPTION.rst
odoo10_addon_auth_signup_verify_email-10.0.2.0.0.dist-info/METADATA
odoo10_addon_auth_signup_verify_email-10.0.2.0.0.dist-info/RECORD
odoo10_addon_auth_signup_verify_email-10.0.2.0.0.dist-info/WHEEL
odoo10_addon_auth_signup_verify_email-10.0.2.0.0.dist-info/metadata.json
odoo10_addon_auth_signup_verify_email-10.0.2.0.0.dist-info/namespace_packages.txt
odoo10_addon_auth_signup_verify_email-10.0.2.0.0.dist-info/top_level.txt
