Metadata-Version: 2.0
Name: odoo10-addon-auth-signup-verify-email
Version: 10.0.2.0.0
Summary: Force uninvited users to use a good email for signup
Home-page: http://github.com/OCA/server-tools
Author: Tecnativa, Odoo Community Association (OCA)
Author-email: support@odoo-community.org
License: AGPL-3
Platform: UNKNOWN
Classifier: Programming Language :: Python
Classifier: Framework :: Odoo
Classifier: License :: OSI Approved :: GNU Affero General Public License v3
Requires-Python: ~=2.7
Requires-Dist: email-validator
Requires-Dist: lxml
Requires-Dist: odoo (<10.1dev,>=10.0)
